acdc_nn/__init__.py
acdc_nn/__main__.py
acdc_nn/acdc_nn.py
acdc_nn/cli.py
acdc_nn/cmd.py
acdc_nn/nn.py
acdc_nn/util.py
acdc_nn/weights/acdc_nn_seq.h5
acdc_nn/weights/full_dataset_TL.data-00000-of-00001
acdc_nn/weights/full_dataset_TL.index
acdc_nn-0.0.17.dist-info/LICENSE
acdc_nn-0.0.17.dist-info/METADATA
acdc_nn-0.0.17.dist-info/WHEEL
acdc_nn-0.0.17.dist-info/entry_points.txt
acdc_nn-0.0.17.dist-info/top_level.txt
acdc_nn-0.0.17.dist-info/RECORD
