Metadata-Version: 2.1
Name: acdc-nn
Version: 0.0.17
Summary: A deep learning predictor of protein stability change upon mutation
Home-page: https://github.com/compbiomed-unito/acdc-nn
Author: Giovanni Birolo
Author-email: giovanni.birolo@unito.it
License: UNKNOWN
Platform: UNKNOWN
Classifier: Programming Language :: Python :: 3
Classifier: License :: OSI Approved :: MIT License
Classifier: Operating System :: OS Independent
Requires-Python: >=3.6
License-File: LICENSE
Requires-Dist: Biopython (>=1.78)
Requires-Dist: click (>=7.1.2)
Requires-Dist: ddgun
Requires-Dist: numpy (>=1.19.5)
Requires-Dist: pandas (>=1.1.5)
Requires-Dist: silence-tensorflow (>=1.1.1)
Requires-Dist: tensorflow (>=2.3.1)
